{
  "race_status": {
    "timestamp": "86:58.100",
    "current_lap": 57,
    "total_laps": 57,
    "safety_car": "NONE",
    "weather": "WET"
  },
  "agents": [
    {
      "id": "Bortoleto",
      "team": "Audi",
      "rank": 1,
      "position": [
        800.0,
        181.62882513652653
      ],
      "status": "RACING",
      "lap_data": {
        "current_lap": 57,
        "last_lap_time": "1:25.800",
        "fastest_lap_time": "0:13.899"
      },
      "vehicle_state": {
        "battery_soc": 0.0,
        "fuel_remaining_mj": 351.56,
        "aero_mode": "X-MODE",
        "mom_available": true,
        "tyre_life": 0.59,
        "tyre_compound": "intermediate",
        "tyre_temp": 109.9,
        "mom_active": true,
        "on_cliff": false,
        "pit_stops_made": 5
      }
    },
    {
      "id": "Gasly",
      "team": "Audi",
      "rank": 2,
      "position": [
        800.0,
        614.3164648987245
      ],
      "status": "RACING",
      "lap_data": {
        "current_lap": 57,
        "last_lap_time": "1:22.000",
        "fastest_lap_time": "0:12.699"
      },
      "vehicle_state": {
        "battery_soc": 0.0,
        "fuel_remaining_mj": 342.94,
        "aero_mode": "X-MODE",
        "mom_available": true,
        "tyre_life": 0.6,
        "tyre_compound": "intermediate",
        "tyre_temp": 109.4,
        "mom_active": true,
        "on_cliff": false,
        "pit_stops_made": 5
      }
    },
    {
      "id": "Norris",
      "team": "McLaren",
      "rank": 3,
      "position": [
        796.5277191232424,
        705.5556494028122
      ],
      "status": "RACING",
      "lap_data": {
        "current_lap": 57,
        "last_lap_time": "1:22.100",
        "fastest_lap_time": "0:11.899"
      },
      "vehicle_state": {
        "battery_soc": 0.0,
        "fuel_remaining_mj": 346.17,
        "aero_mode": "Z-MODE",
        "mom_available": true,
        "tyre_life": 0.6,
        "tyre_compound": "intermediate",
        "tyre_temp": 110.4,
        "mom_active": false,
        "on_cliff": false,
        "pit_stops_made": 5
      }
    },
    {
      "id": "Sainz",
      "team": "Williams",
      "rank": 4,
      "position": [
        800.0,
        698.5233158840779
      ],
      "status": "RACING",
      "lap_data": {
        "current_lap": 57,
        "last_lap_time": "1:22.500",
        "fastest_lap_time": "0:12.299"
      },
      "vehicle_state": {
        "battery_soc": 0.0,
        "fuel_remaining_mj": 347.27,
        "aero_mode": "Z-MODE",
        "mom_available": true,
        "tyre_life": 0.59,
        "tyre_compound": "intermediate",
        "tyre_temp": 109.2,
        "mom_active": false,
        "on_cliff": false,
        "pit_stops_made": 5
      }
    },
    {
      "id": "Piastri",
      "team": "McLaren",
      "rank": 5,
      "position": [
        513.2439889424527,
        757.9463933654716
      ],
      "status": "RACING",
      "lap_data": {
        "current_lap": 57,
        "last_lap_time": "1:22.100",
        "fastest_lap_time": "0:12.199"
      },
      "vehicle_state": {
        "battery_soc": 0.0,
        "fuel_remaining_mj": 351.42,
        "aero_mode": "Z-MODE",
        "mom_available": true,
        "tyre_life": 0.6,
        "tyre_compound": "intermediate",
        "tyre_temp": 110.7,
        "mom_active": false,
        "on_cliff": false,
        "pit_stops_made": 5
      }
    },
    {
      "id": "Ocon",
      "team": "Haas",
      "rank": 6,
      "position": [
        516.1122377368004,
        759.6673426420801
      ],
      "status": "RACING",
      "lap_data": {
        "current_lap": 57,
        "last_lap_time": "1:22.200",
        "fastest_lap_time": "0:13.099"
      },
      "vehicle_state": {
        "battery_soc": 0.0,
        "fuel_remaining_mj": 349.27,
        "aero_mode": "Z-MODE",
        "mom_available": true,
        "tyre_life": 0.6,
        "tyre_compound": "intermediate",
        "tyre_temp": 110.4,
        "mom_active": false,
        "on_cliff": false,
        "pit_stops_made": 5
      }
    },
    {
      "id": "Alonso",
      "team": "Aston Martin",
      "rank": 7,
      "position": [
        165.93500055749098,
        676.558334262485
      ],
      "status": "RACING",
      "lap_data": {
        "current_lap": 57,
        "last_lap_time": "1:22.300",
        "fastest_lap_time": "0:12.599"
      },
      "vehicle_state": {
        "battery_soc": 0.0,
        "fuel_remaining_mj": 351.16,
        "aero_mode": "Z-MODE",
        "mom_available": true,
        "tyre_life": 0.62,
        "tyre_compound": "intermediate",
        "tyre_temp": 110.5,
        "mom_active": false,
        "on_cliff": false,
        "pit_stops_made": 5
      }
    },
    {
      "id": "Tsunoda",
      "team": "Red Bull",
      "rank": 8,
      "position": [
        177.0056499405011,
        695.0094165675018
      ],
      "status": "RACING",
      "lap_data": {
        "current_lap": 57,
        "last_lap_time": "1:22.300",
        "fastest_lap_time": "0:12.799"
      },
      "vehicle_state": {
        "battery_soc": 0.0,
        "fuel_remaining_mj": 360.34,
        "aero_mode": "Z-MODE",
        "mom_available": true,
        "tyre_life": 0.62,
        "tyre_compound": "intermediate",
        "tyre_temp": 110.4,
        "mom_active": false,
        "on_cliff": false,
        "pit_stops_made": 5
      }
    },
    {
      "id": "Hamilton",
      "team": "Ferrari",
      "rank": 9,
      "position": [
        512.2719851139963,
        380.0
      ],
      "status": "RACING",
      "lap_data": {
        "current_lap": 57,
        "last_lap_time": "1:26.700",
        "fastest_lap_time": "0:12.399"
      },
      "vehicle_state": {
        "battery_soc": 0.0,
        "fuel_remaining_mj": 355.71,
        "aero_mode": "X-MODE",
        "mom_available": false,
        "tyre_life": 0.66,
        "tyre_compound": "intermediate",
        "tyre_temp": 107.7,
        "mom_active": false,
        "on_cliff": false,
        "pit_stops_made": 5
      }
    },
    {
      "id": "Bottas",
      "team": "Cadillac",
      "rank": 10,
      "position": [
        695.0298502911728,
        214.9104491264817
      ],
      "status": "RACING",
      "lap_data": {
        "current_lap": 57,
        "last_lap_time": "1:26.700",
        "fastest_lap_time": "0:13.399"
      },
      "vehicle_state": {
        "battery_soc": 0.0,
        "fuel_remaining_mj": 359.19,
        "aero_mode": "X-MODE",
        "mom_available": false,
        "tyre_life": 0.67,
        "tyre_compound": "intermediate",
        "tyre_temp": 108.3,
        "mom_active": false,
        "on_cliff": false,
        "pit_stops_made": 5
      }
    },
    {
      "id": "Albon",
      "team": "Williams",
      "rank": 11,
      "position": [
        418.2491286087893,
        750.0
      ],
      "status": "RACING",
      "lap_data": {
        "current_lap": 56,
        "last_lap_time": "1:23.000",
        "fastest_lap_time": "0:12.999"
      },
      "vehicle_state": {
        "battery_soc": 0.0,
        "fuel_remaining_mj": 362.73,
        "aero_mode": "X-MODE",
        "mom_available": true,
        "tyre_life": 0.68,
        "tyre_compound": "intermediate",
        "tyre_temp": 109.2,
        "mom_active": true,
        "on_cliff": false,
        "pit_stops_made": 5
      }
    },
    {
      "id": "Perez",
      "team": "Cadillac",
      "rank": 12,
      "position": [
        534.2216902192455,
        770.5330141315472
      ],
      "status": "RACING",
      "lap_data": {
        "current_lap": 56,
        "last_lap_time": "1:22.800",
        "fastest_lap_time": "0:13.499"
      },
      "vehicle_state": {
        "battery_soc": 0.0,
        "fuel_remaining_mj": 368.59,
        "aero_mode": "Z-MODE",
        "mom_available": true,
        "tyre_life": 0.66,
        "tyre_compound": "intermediate",
        "tyre_temp": 110.5,
        "mom_active": false,
        "on_cliff": false,
        "pit_stops_made": 5
      }
    },
    {
      "id": "Verstappen",
      "team": "Red Bull",
      "rank": 13,
      "position": [
        176.10871573345037,
        693.5145262224173
      ],
      "status": "RACING",
      "lap_data": {
        "current_lap": 56,
        "last_lap_time": "1:23.800",
        "fastest_lap_time": "0:11.799"
      },
      "vehicle_state": {
        "battery_soc": 0.0,
        "fuel_remaining_mj": 351.03,
        "aero_mode": "Z-MODE",
        "mom_available": true,
        "tyre_life": 0.62,
        "tyre_compound": "intermediate",
        "tyre_temp": 110.3,
        "mom_active": false,
        "on_cliff": false,
        "pit_stops_made": 5
      }
    },
    {
      "id": "Colapinto",
      "team": "Alpine",
      "rank": 14,
      "position": [
        269.5288658650213,
        750.0
      ],
      "status": "RACING",
      "lap_data": {
        "current_lap": 56,
        "last_lap_time": "1:23.200",
        "fastest_lap_time": "0:14.099"
      },
      "vehicle_state": {
        "battery_soc": 0.0,
        "fuel_remaining_mj": 357.46,
        "aero_mode": "X-MODE",
        "mom_available": true,
        "tyre_life": 0.66,
        "tyre_compound": "intermediate",
        "tyre_temp": 110.2,
        "mom_active": true,
        "on_cliff": false,
        "pit_stops_made": 5
      }
    },
    {
      "id": "Russell",
      "team": "Mercedes",
      "rank": 15,
      "position": [
        150.0,
        596.8138660655414
      ],
      "status": "RACING",
      "lap_data": {
        "current_lap": 56,
        "last_lap_time": "1:23.300",
        "fastest_lap_time": "0:12.099"
      },
      "vehicle_state": {
        "battery_soc": 0.0,
        "fuel_remaining_mj": 363.33,
        "aero_mode": "X-MODE",
        "mom_available": true,
        "tyre_life": 0.67,
        "tyre_compound": "intermediate",
        "tyre_temp": 109.4,
        "mom_active": true,
        "on_cliff": false,
        "pit_stops_made": 5
      }
    },
    {
      "id": "Antonelli",
      "team": "Mercedes",
      "rank": 16,
      "position": [
        150.0,
        637.397306867828
      ],
      "status": "RACING",
      "lap_data": {
        "current_lap": 56,
        "last_lap_time": "1:24.100",
        "fastest_lap_time": "0:13.799"
      },
      "vehicle_state": {
        "battery_soc": 0.0,
        "fuel_remaining_mj": 344.89,
        "aero_mode": "X-MODE",
        "mom_available": false,
        "tyre_life": 0.62,
        "tyre_compound": "intermediate",
        "tyre_temp": 101.0,
        "mom_active": false,
        "on_cliff": false,
        "pit_stops_made": 5
      }
    },
    {
      "id": "Lawson",
      "team": "Racing Bulls",
      "rank": 17,
      "position": [
        273.3425815800168,
        750.0
      ],
      "status": "RACING",
      "lap_data": {
        "current_lap": 56,
        "last_lap_time": "1:23.200",
        "fastest_lap_time": "0:13.599"
      },
      "vehicle_state": {
        "battery_soc": 0.0,
        "fuel_remaining_mj": 367.06,
        "aero_mode": "X-MODE",
        "mom_available": true,
        "tyre_life": 0.66,
        "tyre_compound": "intermediate",
        "tyre_temp": 109.0,
        "mom_active": true,
        "on_cliff": false,
        "pit_stops_made": 5
      }
    },
    {
      "id": "Leclerc",
      "team": "Ferrari",
      "rank": 18,
      "position": [
        158.59990006589112,
        403.43996002635646
      ],
      "status": "RACING",
      "lap_data": {
        "current_lap": 56,
        "last_lap_time": "1:23.900",
        "fastest_lap_time": "0:11.999"
      },
      "vehicle_state": {
        "battery_soc": 0.0,
        "fuel_remaining_mj": 356.89,
        "aero_mode": "Z-MODE",
        "mom_available": false,
        "tyre_life": 0.61,
        "tyre_compound": "intermediate",
        "tyre_temp": 109.7,
        "mom_active": false,
        "on_cliff": false,
        "pit_stops_made": 5
      }
    },
    {
      "id": "Hadjar",
      "team": "Racing Bulls",
      "rank": 19,
      "position": [
        152.2710989897856,
        400.9084395959142
      ],
      "status": "RACING",
      "lap_data": {
        "current_lap": 56,
        "last_lap_time": "1:23.600",
        "fastest_lap_time": "0:13.699"
      },
      "vehicle_state": {
        "battery_soc": 0.0,
        "fuel_remaining_mj": 352.51,
        "aero_mode": "Z-MODE",
        "mom_available": false,
        "tyre_life": 0.62,
        "tyre_compound": "intermediate",
        "tyre_temp": 110.9,
        "mom_active": false,
        "on_cliff": false,
        "pit_stops_made": 5
      }
    },
    {
      "id": "Hulkenberg",
      "team": "Alpine",
      "rank": 20,
      "position": [
        150.0,
        551.8611822684162
      ],
      "status": "RACING",
      "lap_data": {
        "current_lap": 56,
        "last_lap_time": "1:23.500",
        "fastest_lap_time": "0:13.199"
      },
      "vehicle_state": {
        "battery_soc": 0.0,
        "fuel_remaining_mj": 369.88,
        "aero_mode": "X-MODE",
        "mom_available": true,
        "tyre_life": 0.67,
        "tyre_compound": "intermediate",
        "tyre_temp": 109.5,
        "mom_active": true,
        "on_cliff": false,
        "pit_stops_made": 5
      }
    },
    {
      "id": "Stroll",
      "team": "Aston Martin",
      "rank": 21,
      "position": [
        150.0,
        584.5108817670133
      ],
      "status": "RACING",
      "lap_data": {
        "current_lap": 56,
        "last_lap_time": "1:23.400",
        "fastest_lap_time": "0:12.899"
      },
      "vehicle_state": {
        "battery_soc": 0.0,
        "fuel_remaining_mj": 368.18,
        "aero_mode": "X-MODE",
        "mom_available": true,
        "tyre_life": 0.67,
        "tyre_compound": "intermediate",
        "tyre_temp": 110.5,
        "mom_active": true,
        "on_cliff": false,
        "pit_stops_made": 5
      }
    },
    {
      "id": "Bearman",
      "team": "Haas",
      "rank": 22,
      "position": [
        775.1022800940814,
        108.50380015680238
      ],
      "status": "RACING",
      "lap_data": {
        "current_lap": 55,
        "last_lap_time": "1:26.400",
        "fastest_lap_time": "0:15.499"
      },
      "vehicle_state": {
        "battery_soc": 0.0,
        "fuel_remaining_mj": 348.35,
        "aero_mode": "Z-MODE",
        "mom_available": false,
        "tyre_life": 0.7,
        "tyre_compound": "intermediate",
        "tyre_temp": 99.4,
        "mom_active": false,
        "on_cliff": false,
        "pit_stops_made": 5
      }
    }
  ]
}